usageflow/core/__init__.py
usageflow/core/base.py
usageflow/core/socket_manager.py
usageflow/core/types.py
usageflow_core-0.3.4.dist-info/METADATA
usageflow_core-0.3.4.dist-info/WHEEL
usageflow_core-0.3.4.dist-info/top_level.txt
usageflow_core-0.3.4.dist-info/RECORD
